LICENSE
MANIFEST.in
README.rst
setup.py
budgetdatapackage/__init__.py
budgetdatapackage/datapackage.py
budgetdatapackage/resource.py
budgetdatapackage/utils.py
budgetdatapackage.egg-info/PKG-INFO
budgetdatapackage.egg-info/SOURCES.txt
budgetdatapackage.egg-info/dependency_links.txt
budgetdatapackage.egg-info/requires.txt
budgetdatapackage.egg-info/top_level.txt
budgetdatapackage/data/countries.json
budgetdatapackage/data/currencies.json
budgetdatapackage/data/granularities.json
budgetdatapackage/data/statuses.json
budgetdatapackage/data/types.json