Metadata-Version: 1.1
Name: budgetdatapackage
Version: 0.0.3
Summary: Manage and load Budget Data Packages
Home-page: https://github.com/tryggvib/budgetdatapackage
Author: Tryggvi Björgvinsson
Author-email: tryggvi.bjorgvinsson@okfn.org
License: GPLv3
Platform: UNKNOWN
Classifier: Development Status :: 4 - Beta
Classifier: Intended Audience :: Developers
Classifier: License :: OSI Approved :: GNU General Public License v3 (GPLv3)
Classifier: Operating System :: OS Independent
Classifier: Programming Language :: Python
Classifier: Programming Language :: Python :: 2
Classifier: Programming Language :: Python :: 3
Classifier: Topic :: Software Development :: Libraries :: Python Modules
Classifier: Topic :: Utilities
